{
  "$schema": "https://json-schema.org/draft/2020-12/schema",
  "$id": "https://dmc12.ai/schemas/common.json",
  "title": "DMC-12 Common Definitions v0.2.0",
  "description": "Shared $defs (Money, FeePayee, FeeKind, PriceLine, FeeRule, OutTheDoorEstimate, NegotiationState, RejectionReason) referenced by quote, negotiation, and pricing-disclosure schemas. v0.2.0 adds OutTheDoorEstimate — the itemized out-the-door object carried on quote output (v0.5 cut).",
  "$defs": {
    "Money": {
      "type": "object",
      "additionalProperties": false,
      "required": ["amount", "currency"],
      "properties": {
        "amount":   {"type": "number", "minimum": 0},
        "currency": {"type": "string", "pattern": "^[A-Z]{3}$"}
      }
    },
    "FeePayee": {
      "enum": ["government", "dealer", "manufacturer", "third_party"]
    },
    "FeeKind": {
      "enum": [
        "vehicle_price", "tax", "title", "registration", "doc",
        "addon", "transport", "rebate", "discount",
        "trade_credit", "down_payment", "lien_payoff", "interest"
      ]
    },
    "PriceLine": {
      "type": "object",
      "additionalProperties": false,
      "required": ["label", "kind", "payee", "amount"],
      "properties": {
        "label":           {"type": "string", "maxLength": 80},
        "kind":            {"$ref": "#/$defs/FeeKind"},
        "payee":           {"$ref": "#/$defs/FeePayee"},
        "amount":          {"$ref": "#/$defs/Money"},
        "statutory_basis": {"type": "string"},
        "negotiable":      {"type": "boolean", "default": false}
      }
    },
    "FeeRule": {
      "description": "Storage shape for an entry in fee_schedules.fee_lines. The compose step in get_pricing_disclosure converts a FeeRule into a PriceLine by either copying the fixed amount or computing rate × applicable_base. PriceLine is the OUTPUT shape (every line has a concrete amount); FeeRule is the INPUT shape (a line may carry either a fixed amount or a percentage rate).",
      "type": "object",
      "additionalProperties": false,
      "required": ["label", "kind", "payee"],
      "oneOf": [
        {"required": ["amount"], "not": {"required": ["rate"]}},
        {"required": ["rate"],   "not": {"required": ["amount"]}}
      ],
      "properties": {
        "label":           {"type": "string", "maxLength": 80},
        "kind":            {"$ref": "#/$defs/FeeKind"},
        "payee":           {"$ref": "#/$defs/FeePayee"},
        "amount":          {"$ref": "#/$defs/Money"},
        "rate":            {
          "type": "number",
          "minimum": 0,
          "maximum": 1,
          "description": "Decimal rate (e.g. 0.0685 = 6.85%). Applied to the rule's applicable_base."
        },
        "applicable_base": {
          "enum": ["vehicle_price", "vehicle_price_plus_addons",
                   "subtotal_pre_tax"],
          "default": "subtotal_pre_tax",
          "description": "Which prior PriceLine sum the rate is multiplied against. Only meaningful when rate is set."
        },
        "statutory_basis": {"type": "string"},
        "negotiable":      {"type": "boolean", "default": false}
      }
    },
    "OutTheDoorEstimate": {
      "description": "Itemized, non-binding out-the-door estimate carried on quote output (v0.5). Flattens the standalone pricing_disclosure shape: the OTD total is promoted to top-level amount/currency, and the itemized price_lines + fees_total/taxes_total + disclosure metadata are carried alongside. subtotal is intentionally omitted — it is derivable as amount - taxes_total.amount. estimate is always true; quoted_price (on the quote, not here) remains the only committed figure.",
      "type": "object",
      "additionalProperties": false,
      "required": ["amount", "currency", "price_lines", "fees_total",
                   "taxes_total", "estimate", "jurisdiction", "as_of"],
      "properties": {
        "amount":              {"type": "number", "minimum": 0,
                                "description": "The out-the-door total (vehicle price + fees + taxes). Equals the sum of every price_lines amount."},
        "currency":            {"type": "string", "pattern": "^[A-Z]{3}$"},
        "price_lines":         {"type": "array",
                                "items": {"$ref": "#/$defs/PriceLine"},
                                "description": "Itemized line items bridging quoted_price to amount: the vehicle_price line plus each fee/tax PriceLine."},
        "fees_total":          {"$ref": "#/$defs/Money",
                                "description": "Sum of dealer-payee, non-vehicle fee lines (e.g. the doc fee)."},
        "taxes_total":         {"$ref": "#/$defs/Money",
                                "description": "Sum of all tax-kind lines."},
        "estimate":            {"const": true,
                                "description": "Always true. The OTD is non-binding; only quoted_price is committed."},
        "jurisdiction":        {"type": "string", "pattern": "^[A-Z]{2}-[A-Z0-9]+$",
                                "description": "Tax jurisdiction the estimate was computed for (e.g. US-UT)."},
        "as_of":               {"type": "string", "format": "date-time",
                                "description": "When the estimate was composed (the fee schedule + tax rate in effect at this instant)."},
        "disclosure_form_url": {"type": "string", "format": "uri",
                                "description": "Optional link to the jurisdiction's official OTD disclosure form."}
      }
    },
    "NegotiationState": {
      "enum": ["proposed", "countered", "accepted",
               "rejected", "expired", "withdrawn"]
    },
    "RejectionReason": {
      "enum": ["below_reserve", "expired", "max_rounds_exceeded",
               "vehicle_unavailable", "policy_violation",
               "customer_withdrew"]
    }
  }
}
